{"bbox": {"AP": 10.178217821782178, "AP50": 12.541254125412541, "AP75": 10.726072607260726, "APs": NaN, "APm": 0.0, "APl": 11.465346534653463}, "_runtime": 317, "_timestamp": 1635506581, "_step": 24, "data_time": 0.003394316999219882, "eta_seconds": 0.0, "fast_rcnn/cls_accuracy": 0.908203125, "fast_rcnn/false_negative": 0.9529346622369879, "fast_rcnn/fg_cls_accuracy": 0.04706533776301218, "iteration": 249, "loss_box_reg": 0.3433019518852234, "loss_cls": 0.22309742122888565, "loss_rpn_cls": 0.012747911270707846, "loss_rpn_loc": 0.006171122193336487, "lr": 0.000249001, "roi_head/num_bg_samples": 115.75, "roi_head/num_fg_samples": 12.25, "rpn/num_neg_anchors": 252.0, "rpn/num_pos_anchors": 4.0, "time": 1.15333392499997, "total_loss": 0.5747752066381508, "./test_imgs/WhatsApp Image 2021-10-19 at 21.27.06.jpeg": {"_type": "image-file", "path": "media/images/test_imgs/WhatsApp Image 2021-10-19 at 21.27.06.jpeg_14_f966cd2afffd91708300.png", "sha256": "f966cd2afffd91708300a08a1c8c23f03f5cb0f19841ac69a05d11b096ce6366", "size": 1550047, "format": "png", "width": 1600, "height": 1200}, "./test_imgs/WhatsApp Image 2021-10-19 at 21.27.07 (1).jpeg": {"_type": "image-file", "path": "media/images/test_imgs/WhatsApp Image 2021-10-19 at 21.27.07 (1).jpeg_15_2a13f0671b106968cfaa.png", "sha256": "2a13f0671b106968cfaad02afa1ee6397197785b39d366f990d3220908cea1ad", "size": 825394, "format": "png", "width": 1600, "height": 1200}, "./test_imgs/WhatsApp Image 2021-10-19 at 21.27.09 (1).jpeg": {"_type": "image-file", "path": "media/images/test_imgs/WhatsApp Image 2021-10-19 at 21.27.09 (1).jpeg_16_37de63ec79cabd7298f5.png", "sha256": "37de63ec79cabd7298f5a6f6bfec752946722be2eeb2f430c0a62219231d20f3", "size": 1345183, "format": "png", "width": 1200, "height": 1600}, "./test_imgs/WhatsApp Image 2021-10-19 at 21.27.07.jpeg": {"_type": "image-file", "path": "media/images/test_imgs/WhatsApp Image 2021-10-19 at 21.27.07.jpeg_17_c361db796d0c2a3acfcb.png", "sha256": "c361db796d0c2a3acfcba18dab3c72471d3f041e9225fa03562e29296e1ac9dc", "size": 2294491, "format": "png", "width": 1600, "height": 1200}, "./test_imgs/WhatsApp Image 2021-10-19 at 21.27.09 (2).jpeg": {"_type": "image-file", "path": "media/images/test_imgs/WhatsApp Image 2021-10-19 at 21.27.09 (2).jpeg_18_695d7c9e69953c15b52c.png", "sha256": "695d7c9e69953c15b52ce9108c81c535544730a0d36bcd99b3920bbb36016b2b", "size": 2053321, "format": "png", "width": 1200, "height": 1600}, "./test_imgs/WhatsApp Image 2021-10-19 at 21.27.08.jpeg": {"_type": "image-file", "path": "media/images/test_imgs/WhatsApp Image 2021-10-19 at 21.27.08.jpeg_19_da45647c645f27d0a0a6.png", "sha256": "da45647c645f27d0a0a6ca1393d111bc9edbc3fcef2cce0a38c28d4a40c0743f", "size": 1810337, "format": "png", "width": 1200, "height": 1600}, "./test_imgs/WhatsApp Image 2021-10-19 at 21.27.08 (1).jpeg": {"_type": "image-file", "path": "media/images/test_imgs/WhatsApp Image 2021-10-19 at 21.27.08 (1).jpeg_20_73e78addb754facbbbbb.png", "sha256": "73e78addb754facbbbbb3fac4b35aa17b9a3626bf478dfcd8c6177743936d7fc", "size": 2183134, "format": "png", "width": 1200, "height": 1600}, "./test_imgs/WhatsApp Image 2021-10-19 at 21.27.09.jpeg": {"_type": "image-file", "path": "media/images/test_imgs/WhatsApp Image 2021-10-19 at 21.27.09.jpeg_21_045796f5b7ef7214e768.png", "sha256": "045796f5b7ef7214e76850a3ad84ea9b54b449dcdf269d1128f9fef58c972c58", "size": 877377, "format": "png", "width": 1200, "height": 1600}, "RMSE": 208852.3125, "MSE": 43619287040.0, "PSNR": 5.217153072357178, "_wandb": {"runtime": 318}}