{"data_time": 0.0026377230001344287, "eta_seconds": 513.2972968799004, "fast_rcnn/cls_accuracy": 0.54296875, "fast_rcnn/false_negative": 0.47017543859649125, "fast_rcnn/fg_cls_accuracy": 0.5298245614035088, "iteration": 19, "loss_box_reg": 0.3395158499479294, "loss_cls": 0.6843304336071014, "loss_rpn_cls": 0.02749764360487461, "loss_rpn_loc": 0.008080338360741735, "lr": 9.7405e-06, "roi_head/num_bg_samples": 116.75, "roi_head/num_fg_samples": 11.25, "rpn/num_neg_anchors": 251.75, "rpn/num_pos_anchors": 4.25, "time": 1.0693693684997925, "total_loss": 1.1293808468617499}
{"data_time": 0.0024523865004084655, "eta_seconds": 473.8005922499997, "fast_rcnn/cls_accuracy": 0.828125, "fast_rcnn/false_negative": 0.8136574074074074, "fast_rcnn/fg_cls_accuracy": 0.1863425925925926, "iteration": 39, "loss_box_reg": 0.3196936696767807, "loss_cls": 0.5805265009403229, "loss_rpn_cls": 0.028030996210873127, "loss_rpn_loc": 0.005100801354274154, "lr": 1.97305e-05, "roi_head/num_bg_samples": 117.25, "roi_head/num_fg_samples": 10.75, "rpn/num_neg_anchors": 252.25, "rpn/num_pos_anchors": 3.75, "time": 1.0141702855003132, "total_loss": 0.9331521701533347}
{"data_time": 0.002398104499661713, "eta_seconds": 446.2349256201378, "fast_rcnn/cls_accuracy": 0.90625, "fast_rcnn/false_negative": 1.0, "fast_rcnn/fg_cls_accuracy": 0.0, "iteration": 59, "loss_box_reg": 0.34007371962070465, "loss_cls": 0.4533393234014511, "loss_rpn_cls": 0.021388689056038857, "loss_rpn_loc": 0.007183062378317118, "lr": 2.9720499999999998e-05, "roi_head/num_bg_samples": 116.0, "roi_head/num_fg_samples": 12.0, "rpn/num_neg_anchors": 252.25, "rpn/num_pos_anchors": 3.75, "time": 0.9550493934998485, "total_loss": 0.8343640197999775}
{"data_time": 0.0025991749994318525, "eta_seconds": 425.95151991013154, "fast_rcnn/cls_accuracy": 0.90234375, "fast_rcnn/false_negative": 1.0, "fast_rcnn/fg_cls_accuracy": 0.0, "iteration": 79, "loss_box_reg": 0.38268613815307617, "loss_cls": 0.32053273916244507, "loss_rpn_cls": 0.022447208873927593, "loss_rpn_loc": 0.006845266791060567, "lr": 3.9710500000000005e-05, "roi_head/num_bg_samples": 115.5, "roi_head/num_fg_samples": 12.5, "rpn/num_neg_anchors": 252.0, "rpn/num_pos_anchors": 4.0, "time": 1.0030264715001067, "total_loss": 0.7363104162504897}
{"data_time": 0.002586232500107144, "eta_seconds": 412.7407640000456, "fast_rcnn/cls_accuracy": 0.93359375, "fast_rcnn/false_negative": 1.0, "fast_rcnn/fg_cls_accuracy": 0.0, "iteration": 99, "loss_box_reg": 0.27476611733436584, "loss_cls": 0.249890498816967, "loss_rpn_cls": 0.03470320254564285, "loss_rpn_loc": 0.006413396913558245, "lr": 4.97005e-05, "roi_head/num_bg_samples": 119.5, "roi_head/num_fg_samples": 8.5, "rpn/num_neg_anchors": 251.25, "rpn/num_pos_anchors": 4.75, "time": 1.1302638419992945, "total_loss": 0.5889364453032613}
{"data_time": 0.002568764499756071, "eta_seconds": 390.8157950301029, "fast_rcnn/cls_accuracy": 0.890625, "fast_rcnn/false_negative": 1.0, "fast_rcnn/fg_cls_accuracy": 0.0, "iteration": 119, "loss_box_reg": 0.3830338567495346, "loss_cls": 0.28286661207675934, "loss_rpn_cls": 0.03749745711684227, "loss_rpn_loc": 0.007077774032950401, "lr": 5.96905e-05, "roi_head/num_bg_samples": 114.25, "roi_head/num_fg_samples": 13.75, "rpn/num_neg_anchors": 251.5, "rpn/num_pos_anchors": 4.5, "time": 1.0242920495002181, "total_loss": 0.7465402858797461}
{"data_time": 0.002370707500631397, "eta_seconds": 369.3150570602302, "fast_rcnn/cls_accuracy": 0.90234375, "fast_rcnn/false_negative": 1.0, "fast_rcnn/fg_cls_accuracy": 0.0, "iteration": 139, "loss_box_reg": 0.3651200234889984, "loss_cls": 0.26297786831855774, "loss_rpn_cls": 0.023429330438375473, "loss_rpn_loc": 0.004794640466570854, "lr": 6.96805e-05, "roi_head/num_bg_samples": 115.5, "roi_head/num_fg_samples": 12.5, "rpn/num_neg_anchors": 252.25, "rpn/num_pos_anchors": 3.75, "time": 0.9928951910005708, "total_loss": 0.6669268894474953}
{"data_time": 0.0025437479998799972, "eta_seconds": 349.5086013301079, "fast_rcnn/cls_accuracy": 0.916015625, "fast_rcnn/false_negative": 1.0, "fast_rcnn/fg_cls_accuracy": 0.0, "iteration": 159, "loss_box_reg": 0.30420032143592834, "loss_cls": 0.229948028922081, "loss_rpn_cls": 0.019720131531357765, "loss_rpn_loc": 0.00853672786615789, "lr": 7.967050000000001e-05, "roi_head/num_bg_samples": 117.25, "roi_head/num_fg_samples": 10.75, "rpn/num_neg_anchors": 250.0, "rpn/num_pos_anchors": 6.0, "time": 1.038839611000185, "total_loss": 0.5925781347323209}
{"data_time": 0.0024844444997143, "eta_seconds": 329.5749347200035, "fast_rcnn/cls_accuracy": 0.908203125, "fast_rcnn/false_negative": 1.0, "fast_rcnn/fg_cls_accuracy": 0.0, "iteration": 179, "loss_box_reg": 0.3429698050022125, "loss_cls": 0.22736947238445282, "loss_rpn_cls": 0.01051349751651287, "loss_rpn_loc": 0.007487219292670488, "lr": 8.966049999999999e-05, "roi_head/num_bg_samples": 116.25, "roi_head/num_fg_samples": 11.75, "rpn/num_neg_anchors": 251.75, "rpn/num_pos_anchors": 4.25, "time": 1.0638013679999858, "total_loss": 0.581233364820946}
{"data_time": 0.0025709924993861932, "eta_seconds": 309.91496984997866, "fast_rcnn/cls_accuracy": 0.90234375, "fast_rcnn/false_negative": 1.0, "fast_rcnn/fg_cls_accuracy": 0.0, "iteration": 199, "loss_box_reg": 0.37483108043670654, "loss_cls": 0.2351394146680832, "loss_rpn_cls": 0.013180486857891083, "loss_rpn_loc": 0.00463590188883245, "lr": 9.96505e-05, "roi_head/num_bg_samples": 115.5, "roi_head/num_fg_samples": 12.5, "rpn/num_neg_anchors": 252.5, "rpn/num_pos_anchors": 3.5, "time": 1.0594988004995685, "total_loss": 0.628597158822231}
{"data_time": 0.00254523299918219, "eta_seconds": 291.13768753984914, "fast_rcnn/cls_accuracy": 0.9296875, "fast_rcnn/false_negative": 1.0, "fast_rcnn/fg_cls_accuracy": 0.0, "iteration": 219, "loss_box_reg": 0.24377861618995667, "loss_cls": 0.17971676588058472, "loss_rpn_cls": 0.03588998317718506, "loss_rpn_loc": 0.009082499891519547, "lr": 0.00010964050000000001, "roi_head/num_bg_samples": 119.0, "roi_head/num_fg_samples": 9.0, "rpn/num_neg_anchors": 249.5, "rpn/num_pos_anchors": 6.5, "time": 1.1347805560008055, "total_loss": 0.4966992328991182}
{"data_time": 0.0024421349990007, "eta_seconds": 270.24062805998255, "fast_rcnn/cls_accuracy": 0.904296875, "fast_rcnn/false_negative": 1.0, "fast_rcnn/fg_cls_accuracy": 0.0, "iteration": 239, "loss_box_reg": 0.3666394054889679, "loss_cls": 0.24928732961416245, "loss_rpn_cls": 0.01602444751188159, "loss_rpn_loc": 0.007162338821217418, "lr": 0.0001196305, "roi_head/num_bg_samples": 115.75, "roi_head/num_fg_samples": 12.25, "rpn/num_neg_anchors": 251.5, "rpn/num_pos_anchors": 4.5, "time": 1.0051366534999033, "total_loss": 0.6588392433477566}
{"data_time": 0.0025319304995718994, "eta_seconds": 249.4528874399839, "fast_rcnn/cls_accuracy": 0.912109375, "fast_rcnn/false_negative": 1.0, "fast_rcnn/fg_cls_accuracy": 0.0, "iteration": 259, "loss_box_reg": 0.3169795274734497, "loss_cls": 0.23894906044006348, "loss_rpn_cls": 0.018918659538030624, "loss_rpn_loc": 0.005959183908998966, "lr": 0.0001296205, "roi_head/num_bg_samples": 116.25, "roi_head/num_fg_samples": 11.75, "rpn/num_neg_anchors": 252.0, "rpn/num_pos_anchors": 4.0, "time": 1.0705318885011366, "total_loss": 0.5699596153572202}
{"data_time": 0.0026265069991495693, "eta_seconds": 228.13226787999156, "fast_rcnn/cls_accuracy": 0.90625, "fast_rcnn/false_negative": 1.0, "fast_rcnn/fg_cls_accuracy": 0.0, "iteration": 279, "loss_box_reg": 0.3381045460700989, "loss_cls": 0.21544338017702103, "loss_rpn_cls": 0.014842334669083357, "loss_rpn_loc": 0.007812200812622905, "lr": 0.00013961050000000003, "roi_head/num_bg_samples": 116.0, "roi_head/num_fg_samples": 12.0, "rpn/num_neg_anchors": 251.75, "rpn/num_pos_anchors": 4.25, "time": 1.0039216990007844, "total_loss": 0.6260605162242427}
{"data_time": 0.0023374934999083052, "eta_seconds": 206.1653169001147, "fast_rcnn/cls_accuracy": 0.8984375, "fast_rcnn/false_negative": 1.0, "fast_rcnn/fg_cls_accuracy": 0.0, "iteration": 299, "loss_box_reg": 0.3870115429162979, "loss_cls": 0.22023582458496094, "loss_rpn_cls": 0.019673049449920654, "loss_rpn_loc": 0.005844525760039687, "lr": 0.0001496005, "roi_head/num_bg_samples": 114.5, "roi_head/num_fg_samples": 13.5, "rpn/num_neg_anchors": 252.0, "rpn/num_pos_anchors": 4.0, "time": 0.9696494394993351, "total_loss": 0.645966115873307}
{"data_time": 0.0024711794985705637, "eta_seconds": 185.03396541005714, "fast_rcnn/cls_accuracy": 0.91015625, "fast_rcnn/false_negative": 1.0, "fast_rcnn/fg_cls_accuracy": 0.0, "iteration": 319, "loss_box_reg": 0.30513541400432587, "loss_cls": 0.21792194992303848, "loss_rpn_cls": 0.02100661676377058, "loss_rpn_loc": 0.00544231035746634, "lr": 0.0001595905, "roi_head/num_bg_samples": 116.5, "roi_head/num_fg_samples": 11.5, "rpn/num_neg_anchors": 252.5, "rpn/num_pos_anchors": 3.5, "time": 0.9594669529997191, "total_loss": 0.5861327894963324}
{"data_time": 0.0023215999999592896, "eta_seconds": 163.41087439999683, "fast_rcnn/cls_accuracy": 0.904296875, "fast_rcnn/false_negative": 0.9857142857142858, "fast_rcnn/fg_cls_accuracy": 0.014285714285714285, "iteration": 339, "loss_box_reg": 0.3665694147348404, "loss_cls": 0.20018663257360458, "loss_rpn_cls": 0.02201868873089552, "loss_rpn_loc": 0.004894664045423269, "lr": 0.00016958050000000002, "roi_head/num_bg_samples": 113.25, "roi_head/num_fg_samples": 14.75, "rpn/num_neg_anchors": 251.25, "rpn/num_pos_anchors": 4.75, "time": 0.8929132840003149, "total_loss": 0.595982397768239}
{"data_time": 0.0023428009990311693, "eta_seconds": 142.95283631994607, "fast_rcnn/cls_accuracy": 0.943359375, "fast_rcnn/false_negative": 0.8819444444444444, "fast_rcnn/fg_cls_accuracy": 0.11805555555555555, "iteration": 359, "loss_box_reg": 0.2444467693567276, "loss_cls": 0.163555808365345, "loss_rpn_cls": 0.02699923235923052, "loss_rpn_loc": 0.00849665841087699, "lr": 0.0001795705, "roi_head/num_bg_samples": 118.75, "roi_head/num_fg_samples": 9.25, "rpn/num_neg_anchors": 250.0, "rpn/num_pos_anchors": 6.0, "time": 0.9694219940001858, "total_loss": 0.430504443065729}
{"data_time": 0.0025900275004460127, "eta_seconds": 122.03201958009231, "fast_rcnn/cls_accuracy": 0.923828125, "fast_rcnn/false_negative": 0.8931159420289855, "fast_rcnn/fg_cls_accuracy": 0.1068840579710145, "iteration": 379, "loss_box_reg": 0.28495244681835175, "loss_cls": 0.1939220204949379, "loss_rpn_cls": 0.023694414645433426, "loss_rpn_loc": 0.00700162909924984, "lr": 0.0001895605, "roi_head/num_bg_samples": 117.25, "roi_head/num_fg_samples": 10.75, "rpn/num_neg_anchors": 251.25, "rpn/num_pos_anchors": 4.75, "time": 0.8650287555001341, "total_loss": 0.5750938764540479}
{"data_time": 0.0024132034996000584, "eta_seconds": 101.78979770007572, "fast_rcnn/cls_accuracy": 0.921875, "fast_rcnn/false_negative": 0.8991596638655461, "fast_rcnn/fg_cls_accuracy": 0.10084033613445378, "iteration": 399, "loss_box_reg": 0.2619754374027252, "loss_cls": 0.19838985800743103, "loss_rpn_cls": 0.021411916241049767, "loss_rpn_loc": 0.010493286419659853, "lr": 0.00019955050000000003, "roi_head/num_bg_samples": 116.75, "roi_head/num_fg_samples": 11.25, "rpn/num_neg_anchors": 251.25, "rpn/num_pos_anchors": 4.75, "time": 1.0199542929995005, "total_loss": 0.5339406033745036}
{"data_time": 0.002308053999513504, "eta_seconds": 81.08710951993999, "fast_rcnn/cls_accuracy": 0.931640625, "fast_rcnn/false_negative": 0.9616477272727273, "fast_rcnn/fg_cls_accuracy": 0.03835227272727273, "iteration": 419, "loss_box_reg": 0.24383005499839783, "loss_cls": 0.19793279469013214, "loss_rpn_cls": 0.01908729039132595, "loss_rpn_loc": 0.0077697045635432005, "lr": 0.00020954049999999998, "roi_head/num_bg_samples": 118.25, "roi_head/num_fg_samples": 9.75, "rpn/num_neg_anchors": 251.25, "rpn/num_pos_anchors": 4.75, "time": 0.973826575500425, "total_loss": 0.5074056275188923}
{"data_time": 0.002289654500600591, "eta_seconds": 60.685272959981376, "fast_rcnn/cls_accuracy": 0.927734375, "fast_rcnn/false_negative": 0.7571428571428571, "fast_rcnn/fg_cls_accuracy": 0.24285714285714285, "iteration": 439, "loss_box_reg": 0.26940523087978363, "loss_cls": 0.18396995216608047, "loss_rpn_cls": 0.01700324472039938, "loss_rpn_loc": 0.009371005930006504, "lr": 0.0002195305, "roi_head/num_bg_samples": 115.75, "roi_head/num_fg_samples": 12.25, "rpn/num_neg_anchors": 251.0, "rpn/num_pos_anchors": 5.0, "time": 0.9200945955008137, "total_loss": 0.4975695463363081}
{"data_time": 0.0024296460005643894, "eta_seconds": 40.456848639987584, "fast_rcnn/cls_accuracy": 0.919921875, "fast_rcnn/false_negative": 0.6659090909090909, "fast_rcnn/fg_cls_accuracy": 0.3340909090909091, "iteration": 459, "loss_box_reg": 0.3043018728494644, "loss_cls": 0.20836465060710907, "loss_rpn_cls": 0.02611477952450514, "loss_rpn_loc": 0.012556110508739948, "lr": 0.00022952050000000002, "roi_head/num_bg_samples": 116.25, "roi_head/num_fg_samples": 11.75, "rpn/num_neg_anchors": 250.75, "rpn/num_pos_anchors": 5.25, "time": 1.0018057895013044, "total_loss": 0.5675774877890944}
{"data_time": 0.002490636999027629, "eta_seconds": 20.228424319993792, "fast_rcnn/cls_accuracy": 0.9140625, "fast_rcnn/false_negative": 0.7361111111111112, "fast_rcnn/fg_cls_accuracy": 0.2638888888888889, "iteration": 479, "loss_box_reg": 0.29248693585395813, "loss_cls": 0.21102654188871384, "loss_rpn_cls": 0.015940236393362284, "loss_rpn_loc": 0.005175712518393993, "lr": 0.0002395105, "roi_head/num_bg_samples": 115.5, "roi_head/num_fg_samples": 12.5, "rpn/num_neg_anchors": 252.25, "rpn/num_pos_anchors": 3.75, "time": 1.0141022729985707, "total_loss": 0.5157401214819402}
{"data_time": 0.0024042680006459705, "eta_seconds": 0.0, "fast_rcnn/cls_accuracy": 0.93359375, "fast_rcnn/false_negative": 0.7636363636363637, "fast_rcnn/fg_cls_accuracy": 0.23636363636363636, "iteration": 499, "loss_box_reg": 0.23782850056886673, "loss_cls": 0.20043321698904037, "loss_rpn_cls": 0.01570486044511199, "loss_rpn_loc": 0.0076910522766411304, "lr": 0.0002495005, "roi_head/num_bg_samples": 117.25, "roi_head/num_fg_samples": 10.75, "rpn/num_neg_anchors": 251.0, "rpn/num_pos_anchors": 5.0, "time": 1.072055048999573, "total_loss": 0.4800337525084615}
